crprint/__init__.py
crprint/main.py
Terry_CRPrint-0.2.0.dist-info/METADATA
Terry_CRPrint-0.2.0.dist-info/WHEEL
Terry_CRPrint-0.2.0.dist-info/top_level.txt
Terry_CRPrint-0.2.0.dist-info/RECORD
