Metadata-Version: 2.1
Name: Terry-CRPrint
Version: 0.2.0
